icedtools/__init__.py
icedtools-0.0.1.dist-info/LICENSE
icedtools-0.0.1.dist-info/WHEEL
icedtools-0.0.1.dist-info/METADATA
icedtools-0.0.1.dist-info/RECORD
