Metadata-Version: 2.1
Name: icedtools
Version: 0.0.1
Summary: Let's write some code
Home-page: https://github.com/iceraj/icedtools
Author: Ivica Ceraj
Author-email: iceraj@gmail.com
Classifier: License :: OSI Approved :: MIT License
